kriek/__init__.py
kriek/api/__init__.py
kriek/api/abort.py
kriek/api/api.py
kriek/api/exceptions.py
kriek/api/module.py
kriek/api/response.py
kriek/api/constants/__init__.py
kriek/api/constants/http/__init__.py
kriek/api/constants/http/meaning.py
kriek/api/constants/http/verbs.py
kriek/cli/__init__.py
kriek/cli/cli.py
kriek/cli/const.py
kriek/cli/commands/__init__.py
kriek/cli/commands/create.py
kriek/examples/new_project/settings.py
kriek/examples/new_project/wsgi.py
kriek/examples/new_project/api/__init__.py
kriek/examples/new_project/api/resource/__init__.py
kriek/examples/new_project/api/resource/account.py
kriek/examples/new_project/api/resource/swagger.py
kriek-0.2.dist-info/METADATA
kriek-0.2.dist-info/WHEEL
kriek-0.2.dist-info/entry_points.txt
kriek-0.2.dist-info/top_level.txt
kriek-0.2.dist-info/RECORD
