Metadata-Version: 2.1
Name: kriek
Version: 0.2
Summary: Fast and simple WSGI-framework to develop restoring api.
Home-page: http://kriek.sylvan.ovh/
Author: Sylvan LE DEUNFF
Author-email: sledeunf@gmail.com
License: MIT
Platform: any
Requires-Dist: python-magic
Requires-Dist: Werkzeug
